Workbook

Sheet Start Here
A1: LinkedIn Performance Assessment: Q1 and Q2 2026
A2: Shrikant Ahire | linkedin.com/in/shrikant-ahire87 | Prepared 4 Oct 2026 | Covers 1 Jan to 30 Jun 2026
A4: THE VERDICT IN 5 LINES
A5: 1. You barely posted in Q1 and Q2. Only one original post can be identified in six months: your Bramasol job announcement on 2 March.
A6: 2. That one post worked. Its week delivered 794 impressions and 48 reactions plus comments, about 4x the median post for small accounts and a 6% engagement rate (benchmark 2.56%).
A7: 3. Nothing followed it, so reach fell to 150, then 23, then 73, then 22 impressions a week. January, February and May show no activity at all.
A8: 4. None of your Q1 and Q2 content was about Claude or AI, so your personal brand goal had no content behind it yet.
A9: 5. Your network responds when you show up. For the next 90 days, post 3 times a week with a named 'Claude for Sales Ops' series and track every post.
A11: HOW THIS WORKBOOK IS ORGANISED (read left to right)
A12: Tab | B12: What it shows | C12: Use it to | D12: Key question it answers
A13: Dashboard | B13: KPI tiles, Q1 vs Q2 comparison, weekly impressions chart, scores against benchmarks | C13: Get the picture in 30 seconds | D13: How did I do overall?
A14: Weekly Data | B14: Every week from 29 Dec 2025 to 5 Jul 2026, green where LinkedIn reported numbers, grey where it did not | C14: See the trend and the gaps | D14: When did I get reach and when did I go quiet?
A15: Post Log | B15: Every post identified, with reactions, comments and engagement rate. Yellow rows are ready for your export | C15: Compare posts against each other | D15: Which posts worked?
A16: Audience | B16: Who saw your posts, from LinkedIn's weekly recaps | C16: Check you are reaching buyers | D16: Who is actually reading me?
A17: Diagnosis | B17: 10 findings from your own data, rated red, amber or green | C17: Know what to fix first | D17: What went wrong and what went right?
A18: Research Insights | B18: 53 research findings on the LinkedIn algorithm, formats, benchmarks and the AI content space, each with what it means for you | C18: Back every decision with evidence | D18: What does the market data say?
A19: Benchmarks | B19: 20 industry benchmarks with your number beside them where one exists | C19: Set realistic targets | D19: What does good look like for my size?
A20: Action Plan | B20: 18 prioritised actions with target, deadline and a status dropdown | C20: Run the next 90 days | D20: What exactly do I do?
A21: Content Calendar | B21: 13 weeks x 3 posts, Oct to Dec 2026, with topic, format and hook ideas | C21: Never start from a blank page | D21: What do I post this week?
A22: Tracker | B22: Weekly scorecard with targets; fill the yellow cells and it turns green or red on its own | C22: Measure progress every Monday | D22: Am I on track?
A23: Sources & Gaps | B23: Where every number came from and what is missing | C23: Trust the numbers | D23: How reliable is this?
A25: COLOUR KEY
A26: Green cell | B26: Real number LinkedIn reported (from your Gmail recaps or notifications)
A27: Grey cell | B27: No data exists for this period
A28: Yellow cell | B28: Input cell for you to fill in from your LinkedIn export
A29: Green rating | B29: Strength / on target
A30: Amber rating | B30: Watch / needs work
A31: Red rating | B31: Problem / top priority to fix
A33: IMPORTANT: DATA LIMITS
A34: LinkedIn blocks automated access, so these numbers come from the analytics emails LinkedIn sent to your Gmail (5 weekly recaps and 2 post notifications). No figure here is estimated. To complete the picture, export LinkedIn Analytics > Content and Followers (1 Jan to 30 Jun 2026) and paste the numbers into the yellow cells on Post Log and Weekly Data. Every formula and chart updates automatically. Q3 (Jul to Sep) has already ended, so the plan covers the next 90 days (Oct to Dec 2026).

Sheet Dashboard
A1: Dashboard: Q1 vs Q2 2026 at a glance
A2: Every number below is a live formula linked to Weekly Data, Post Log and Benchmarks. Fill the gaps there and this page updates.
A4: HEADLINE NUMBERS
A5: Total impressions (recorded) | C5: Peak week impressions | E5: Original posts identified | G5: Engagement rate (recorded weeks)
A6: =SUM('Weekly Data'!$D$5:$D$32) | C6: =MAX('Weekly Data'!$D$5:$D$32) | E6: =COUNTA('Post Log'!$B$5:$B$40) | G6: ='Weekly Data'!H33
A7: Q1 + Q2, from 5 recap weeks | C7: Week of 2 Mar (job post) | E7: In 26 weeks | G7: Benchmark median 2.56%
A9: Total reactions (recorded) | C9: Total comments (recorded) | E9: Weeks with any reach | G9: Peak week vs small-account median
A10: =SUM('Weekly Data'!$E$5:$E$32) | C10: =SUM('Weekly Data'!$F$5:$F$32) | E10: =COUNTIF('Weekly Data'!$I$5:$I$32,"Recorded") | G10: =MAX('Weekly Data'!$D$5:$D$32)/Benchmarks!$C$8
E11: Out of 28 weeks shown | G11: vs 207 median impressions/post
A13: Q1 vs Q2 COMPARISON
A14: Metric | B14: Q1 (Jan to Mar) | C14: Q2 (Apr to Jun) | D14: Change | E14: Rating | F14: What it means
A15: Impressions (recorded) | B15: =SUMIFS('Weekly Data'!$D$5:$D$32,'Weekly Data'!$C$5:$C$32,"Q1") | C15: =SUMIFS('Weekly Data'!$D$5:$D$32,'Weekly Data'!$C$5:$C$32,"Q2") | D15: =IF(B15=0,"n/a",(C15-B15)/B15) | E15: =IF(B15=0,IF(C15>0,"Up","Flat"),IF(C15>=B15,"Up",IF(C15>=B15*0.5,"Down","Sharp drop"))) | F15: Reach fell sharply because posting stopped after March.
A16: Reactions (recorded) | B16: =SUMIFS('Weekly Data'!$E$5:$E$32,'Weekly Data'!$C$5:$C$32,"Q1") | C16: =SUMIFS('Weekly Data'!$E$5:$E$32,'Weekly Data'!$C$5:$C$32,"Q2") | D16: =IF(B16=0,"n/a",(C16-B16)/B16) | E16: =IF(B16=0,IF(C16>0,"Up","Flat"),IF(C16>=B16,"Up",IF(C16>=B16*0.5,"Down","Sharp drop"))) | F16: Q2 reactions came from weeks with almost no new posts.
A17: Comments (recorded) | B17: =SUMIFS('Weekly Data'!$F$5:$F$32,'Weekly Data'!$C$5:$C$32,"Q1") | C17: =SUMIFS('Weekly Data'!$F$5:$F$32,'Weekly Data'!$C$5:$C$32,"Q2") | D17: =IF(B17=0,"n/a",(C17-B17)/B17) | E17: =IF(B17=0,IF(C17>0,"Up","Flat"),IF(C17>=B17,"Up",IF(C17>=B17*0.5,"Down","Sharp drop"))) | F17: Comments are your strongest signal in Q1: people talk when you share real news.
A18: Weeks with reach | B18: =COUNTIFS('Weekly Data'!$C$5:$C$32,"Q1",'Weekly Data'!$I$5:$I$32,"Recorded") | C18: =COUNTIFS('Weekly Data'!$C$5:$C$32,"Q2",'Weekly Data'!$I$5:$I$32,"Recorded") | D18: =IF(B18=0,"n/a",(C18-B18)/B18) | E18: =IF(B18=0,IF(C18>0,"Up","Flat"),IF(C18>=B18,"Up",IF(C18>=B18*0.5,"Down","Sharp drop"))) | F18: Reach only shows up in weeks you post.
A19: Peak week impressions | B19: =_xlfn.MAXIFS('Weekly Data'!$D$5:$D$32,'Weekly Data'!$C$5:$C$32,"Q1") | C19: =_xlfn.MAXIFS('Weekly Data'!$D$5:$D$32,'Weekly Data'!$C$5:$C$32,"Q2") | D19: =IF(B19=0,"n/a",(C19-B19)/B19) | E19: =IF(B19=0,IF(C19>0,"Up","Flat"),IF(C19>=B19,"Up",IF(C19>=B19*0.5,"Down","Sharp drop"))) | F19: Q2 best week was under 10% of Q1 best week.
A20: Original posts identified | B20: =COUNTIFS('Post Log'!$C$5:$C$40,"Q1") | C20: =COUNTIFS('Post Log'!$C$5:$C$40,"Q2") | D20: =IF(B20=0,"n/a",(C20-B20)/B20) | E20: =IF(B20=0,IF(C20>0,"Up","Flat"),IF(C20>=B20,"Up",IF(C20>=B20*0.5,"Down","Sharp drop"))) | F20: Target from here: 36 posts per quarter (3 a week).
A22: SCORECARD AGAINST BENCHMARKS
A23: Measure | B23: You | C23: Benchmark | D23: Gap | E23: Rating | F23: Benchmark source
A24: Engagement rate (peak week) | B24: ='Weekly Data'!H14 | C24: =Benchmarks!$C$5 | D24: =IFERROR(B24/C24-1,"") | E24: =IF(B24>=C24,"Above",IF(B24>=C24*0.5,"Below","Far below")) | F24: AuthoredUp, 372K posts, 0 to 1K followers
A25: Engagement rate (all recorded weeks) | B25: ='Weekly Data'!H33 | C25: =Benchmarks!$C$5 | D25: =IFERROR(B25/C25-1,"") | E25: =IF(B25>=C25,"Above",IF(B25>=C25*0.5,"Below","Far below")) | F25: AuthoredUp, 372K posts, 0 to 1K followers
A26: Best week impressions vs median post | B26: =MAX('Weekly Data'!$D$5:$D$32) | C26: =Benchmarks!$C$8 | D26: =IFERROR(B26/C26-1,"") | E26: =IF(B26>=C26,"Above",IF(B26>=C26*0.5,"Below","Far below")) | F26: MagicPost June 2026, 0 to 1K followers
A27: Typical week impressions (median of recorded) | B27: =MEDIAN('Weekly Data'!$D$5:$D$32) | C27: =Benchmarks!$C$8 | D27: =IFERROR(B27/C27-1,"") | E27: =IF(B27>=C27,"Above",IF(B27>=C27*0.5,"Below","Far below")) | F27: MagicPost June 2026, 0 to 1K followers
A28: Posts per week (Q1 + Q2 average) | B28: =COUNTA('Post Log'!$B$5:$B$40)/26 | C28: =2 | D28: =IFERROR(B28/C28-1,"") | E28: =IF(B28>=C28,"Above",IF(B28>=C28*0.5,"Below","Far below")) | F28: Buffer: 2 to 5 posts a week adds about 1,182 impressions per post
A30: WEEKLY IMPRESSIONS, JAN TO JUN 2026 (blank bars = no data)

Sheet Weekly Data
A1: Weekly Data: every week of Q1 and Q2 2026
A2: Green = numbers LinkedIn reported in its weekly recap email. Grey = no recap was sent (LinkedIn only sends one when you have impressions). Paste export figures into grey rows and they count everywhere.
A4: Week start | B4: Week end | C4: Quarter | D4: Impressions | E4: Reactions | F4: Comments | G4: Engagements | H4: Engagement rate | I4: Data status | J4: What happened / source
A5: 46020 | B5: 46026 | C5: =IF(A5<DATE(2026,3,30),"Q1","Q2") | G5: =IF(COUNT(E5:F5)=2,E5+F5,"") | H5: =IF(AND(ISNUMBER(G5),N(D5)>0),G5/D5,"") | I5: =IF(ISNUMBER(D5),"Recorded","No data") | J5: No recap. Only security emails from LinkedIn this period; no sign of posting.
A6: 46027 | B6: 46033 | C6: =IF(A6<DATE(2026,3,30),"Q1","Q2") | G6: =IF(COUNT(E6:F6)=2,E6+F6,"") | H6: =IF(AND(ISNUMBER(G6),N(D6)>0),G6/D6,"") | I6: =IF(ISNUMBER(D6),"Recorded","No data") | J6: No recap. Only security emails from LinkedIn this period; no sign of posting.
A7: 46034 | B7: 46040 | C7: =IF(A7<DATE(2026,3,30),"Q1","Q2") | G7: =IF(COUNT(E7:F7)=2,E7+F7,"") | H7: =IF(AND(ISNUMBER(G7),N(D7)>0),G7/D7,"") | I7: =IF(ISNUMBER(D7),"Recorded","No data") | J7: No recap. Only security emails from LinkedIn this period; no sign of posting.
A8: 46041 | B8: 46047 | C8: =IF(A8<DATE(2026,3,30),"Q1","Q2") | G8: =IF(COUNT(E8:F8)=2,E8+F8,"") | H8: =IF(AND(ISNUMBER(G8),N(D8)>0),G8/D8,"") | I8: =IF(ISNUMBER(D8),"Recorded","No data") | J8: No recap. Only security emails from LinkedIn this period; no sign of posting.
A9: 46048 | B9: 46054 | C9: =IF(A9<DATE(2026,3,30),"Q1","Q2") | G9: =IF(COUNT(E9:F9)=2,E9+F9,"") | H9: =IF(AND(ISNUMBER(G9),N(D9)>0),G9/D9,"") | I9: =IF(ISNUMBER(D9),"Recorded","No data") | J9: No recap. Only security emails from LinkedIn this period; no sign of posting.
A10: 46055 | B10: 46061 | C10: =IF(A10<DATE(2026,3,30),"Q1","Q2") | G10: =IF(COUNT(E10:F10)=2,E10+F10,"") | H10: =IF(AND(ISNUMBER(G10),N(D10)>0),G10/D10,"") | I10: =IF(ISNUMBER(D10),"Recorded","No data") | J10: No recap. Only security emails from LinkedIn this period; no sign of posting.
A11: 46062 | B11: 46068 | C11: =IF(A11<DATE(2026,3,30),"Q1","Q2") | G11: =IF(COUNT(E11:F11)=2,E11+F11,"") | H11: =IF(AND(ISNUMBER(G11),N(D11)>0),G11/D11,"") | I11: =IF(ISNUMBER(D11),"Recorded","No data") | J11: No recap. Only security emails from LinkedIn this period; no sign of posting.
A12: 46069 | B12: 46075 | C12: =IF(A12<DATE(2026,3,30),"Q1","Q2") | G12: =IF(COUNT(E12:F12)=2,E12+F12,"") | H12: =IF(AND(ISNUMBER(G12),N(D12)>0),G12/D12,"") | I12: =IF(ISNUMBER(D12),"Recorded","No data") | J12: No recap. Only security emails from LinkedIn this period; no sign of posting.
A13: 46076 | B13: 46082 | C13: =IF(A13<DATE(2026,3,30),"Q1","Q2") | G13: =IF(COUNT(E13:F13)=2,E13+F13,"") | H13: =IF(AND(ISNUMBER(G13),N(D13)>0),G13/D13,"") | I13: =IF(ISNUMBER(D13),"Recorded","No data") | J13: No recap email. LinkedIn's next recap said 794 was 2.2x this week, so roughly 360 impressions here (implied, not entered).
A14: 46083 | B14: 46089 | C14: =IF(A14<DATE(2026,3,30),"Q1","Q2") | D14: 794 | E14: 23 | F14: 25 | G14: =IF(COUNT(E14:F14)=2,E14+F14,"") | H14: =IF(AND(ISNUMBER(G14),N(D14)>0),G14/D14,"") | I14: =IF(ISNUMBER(D14),"Recorded","No data") | J14: PEAK WEEK. Bramasol job announcement posted Mon 2 Mar. LinkedIn: '2.2x impressions and 3.6x reactions more than last week'. Source: recap email 10 Mar.
A15: 46090 | B15: 46096 | C15: =IF(A15<DATE(2026,3,30),"Q1","Q2") | G15: =IF(COUNT(E15:F15)=2,E15+F15,"") | H15: =IF(AND(ISNUMBER(G15),N(D15)>0),G15/D15,"") | I15: =IF(ISNUMBER(D15),"Recorded","No data") | J15: No recap. Post kept collecting comments (23 reactions, 18 comments by 13 Mar).
A16: 46097 | B16: 46103 | C16: =IF(A16<DATE(2026,3,30),"Q1","Q2") | G16: =IF(COUNT(E16:F16)=2,E16+F16,"") | H16: =IF(AND(ISNUMBER(G16),N(D16)>0),G16/D16,"") | I16: =IF(ISNUMBER(D16),"Recorded","No data") | J16: No recap. Post reached 24 reactions, 20 comments by 24 Mar.
A17: 46104 | B17: 46110 | C17: =IF(A17<DATE(2026,3,30),"Q1","Q2") | D17: 150 | E17: 1 | F17: 2 | G17: =IF(COUNT(E17:F17)=2,E17+F17,"") | H17: =IF(AND(ISNUMBER(G17),N(D17)>0),G17/D17,"") | I17: =IF(ISNUMBER(D17),"Recorded","No data") | J17: Source: recap email 31 Mar.
A18: 46111 | B18: 46117 | C18: =IF(A18<DATE(2026,3,30),"Q1","Q2") | D18: 23 | G18: =IF(COUNT(E18:F18)=2,E18+F18,"") | H18: =IF(AND(ISNUMBER(G18),N(D18)>0),G18/D18,"") | I18: =IF(ISNUMBER(D18),"Recorded","No data") | J18: Only impressions shown. Week straddles Q1 and Q2. Source: recap email 7 Apr.
A19: 46118 | B19: 46124 | C19: =IF(A19<DATE(2026,3,30),"Q1","Q2") | G19: =IF(COUNT(E19:F19)=2,E19+F19,"") | H19: =IF(AND(ISNUMBER(G19),N(D19)>0),G19/D19,"") | I19: =IF(ISNUMBER(D19),"Recorded","No data") | J19: No recap. Next recap said 73 was 23.3x this week, so about 3 impressions (implied). Display name changed to 'SK' / 'S. K.' this week.
A20: 46125 | B20: 46131 | C20: =IF(A20<DATE(2026,3,30),"Q1","Q2") | D20: 73 | E20: 3 | F20: 1 | G20: =IF(COUNT(E20:F20)=2,E20+F20,"") | H20: =IF(AND(ISNUMBER(G20),N(D20)>0),G20/D20,"") | I20: =IF(ISNUMBER(D20),"Recorded","No data") | J20: Source: recap email 21 Apr (sent to 'Shreekant'). Name changed to 'Shreekant Aahire' on 12 Apr.
A21: 46132 | B21: 46138 | C21: =IF(A21<DATE(2026,3,30),"Q1","Q2") | G21: =IF(COUNT(E21:F21)=2,E21+F21,"") | H21: =IF(AND(ISNUMBER(G21),N(D21)>0),G21/D21,"") | I21: =IF(ISNUMBER(D21),"Recorded","No data") | J21: No recap. You commented on another post on 25 Apr and got 2 replies.
A22: 46139 | B22: 46145 | C22: =IF(A22<DATE(2026,3,30),"Q1","Q2") | G22: =IF(COUNT(E22:F22)=2,E22+F22,"") | H22: =IF(AND(ISNUMBER(G22),N(D22)>0),G22/D22,"") | I22: =IF(ISNUMBER(D22),"Recorded","No data") | J22: No recap. No LinkedIn emails of any kind in May.
A23: 46146 | B23: 46152 | C23: =IF(A23<DATE(2026,3,30),"Q1","Q2") | G23: =IF(COUNT(E23:F23)=2,E23+F23,"") | H23: =IF(AND(ISNUMBER(G23),N(D23)>0),G23/D23,"") | I23: =IF(ISNUMBER(D23),"Recorded","No data") | J23: No recap. No LinkedIn emails of any kind in May.
A24: 46153 | B24: 46159 | C24: =IF(A24<DATE(2026,3,30),"Q1","Q2") | G24: =IF(COUNT(E24:F24)=2,E24+F24,"") | H24: =IF(AND(ISNUMBER(G24),N(D24)>0),G24/D24,"") | I24: =IF(ISNUMBER(D24),"Recorded","No data") | J24: No recap. No LinkedIn emails of any kind in May.
A25: 46160 | B25: 46166 | C25: =IF(A25<DATE(2026,3,30),"Q1","Q2") | G25: =IF(COUNT(E25:F25)=2,E25+F25,"") | H25: =IF(AND(ISNUMBER(G25),N(D25)>0),G25/D25,"") | I25: =IF(ISNUMBER(D25),"Recorded","No data") | J25: No recap. No LinkedIn emails of any kind in May.
A26: 46167 | B26: 46173 | C26: =IF(A26<DATE(2026,3,30),"Q1","Q2") | G26: =IF(COUNT(E26:F26)=2,E26+F26,"") | H26: =IF(AND(ISNUMBER(G26),N(D26)>0),G26/D26,"") | I26: =IF(ISNUMBER(D26),"Recorded","No data") | J26: No recap. No LinkedIn emails of any kind in May.
A27: 46174 | B27: 46180 | C27: =IF(A27<DATE(2026,3,30),"Q1","Q2") | G27: =IF(COUNT(E27:F27)=2,E27+F27,"") | H27: =IF(AND(ISNUMBER(G27),N(D27)>0),G27/D27,"") | I27: =IF(ISNUMBER(D27),"Recorded","No data") | J27: No recap email.
A28: 46181 | B28: 46187 | C28: =IF(A28<DATE(2026,3,30),"Q1","Q2") | G28: =IF(COUNT(E28:F28)=2,E28+F28,"") | H28: =IF(AND(ISNUMBER(G28),N(D28)>0),G28/D28,"") | I28: =IF(ISNUMBER(D28),"Recorded","No data") | J28: No recap email.
A29: 46188 | B29: 46194 | C29: =IF(A29<DATE(2026,3,30),"Q1","Q2") | G29: =IF(COUNT(E29:F29)=2,E29+F29,"") | H29: =IF(AND(ISNUMBER(G29),N(D29)>0),G29/D29,"") | I29: =IF(ISNUMBER(D29),"Recorded","No data") | J29: No recap. You commented on a Marisa Peer post on 18 Jun and got a reply.
A30: 46195 | B30: 46201 | C30: =IF(A30<DATE(2026,3,30),"Q1","Q2") | G30: =IF(COUNT(E30:F30)=2,E30+F30,"") | H30: =IF(AND(ISNUMBER(G30),N(D30)>0),G30/D30,"") | I30: =IF(ISNUMBER(D30),"Recorded","No data") | J30: No recap email.
A31: 46202 | B31: 46208 | C31: Q2 | D31: 22 | G31: =IF(COUNT(E31:F31)=2,E31+F31,"") | H31: =IF(AND(ISNUMBER(G31),N(D31)>0),G31/D31,"") | I31: =IF(ISNUMBER(D31),"Recorded","No data") | J31: Only impressions shown. Week straddles Q2 and Q3. Source: recap email 7 Jul.
A32: 46209 | B32: 46215 | C32: =IF(A32<DATE(2026,3,30),"Q1","Q2") | G32: =IF(COUNT(E32:F32)=2,E32+F32,"") | H32: =IF(AND(ISNUMBER(G32),N(D32)>0),G32/D32,"") | I32: =IF(ISNUMBER(D32),"Recorded","No data") | J32: No recap email.
A33: TOTAL (recorded weeks) | D33: =SUM(D5:D32) | E33: =SUM(E5:E32) | F33: =SUM(F5:F32) | G33: =SUM(G5:G32) | H33: =IFERROR(SUM(G5:G32)/SUMPRODUCT(ISNUMBER(G5:G32)*1,D5:D32),"") | I33: =COUNTIF(I5:I32,"Recorded")&" of "&ROWS(I5:I32)&" weeks"
A34: Engagement rate = (reactions + comments) / impressions, only for weeks where LinkedIn reported both. Weeks are Monday to Sunday, matching LinkedIn's recap emails. The 30 Mar week (5 of 7 days in Q2) and the 29 Jun week (the only late-June reading) both straddle quarters and are counted in Q2.

Sheet Post Log
A1: Post Log: every post, side by side
A2: Green row = numbers read from LinkedIn notification emails. Yellow rows = paste each post from your LinkedIn Content export (Top posts tab). Engagement rate and rating calculate on their own.
A4: # | B4: Date | C4: Qtr | D4: Topic / first line | E4: Format | F4: Content pillar | G4: Impressions | H4: Reactions | I4: Comments | J4: Reposts | K4: Engagement rate | L4: Rating | M4: Notes / source
A5: 1 | B5: 46083 | C5: =IF(B5="","",IF(MONTH(B5)<=3,"Q1",IF(MONTH(B5)<=6,"Q2",IF(MONTH(B5)<=9,"Q3","Q4")))) | D5: I'm happy to share that I'm starting a new position as Operational Sales Consultant at Bramasol, Inc.! | E5: Job update | F5: Personal milestone | H5: 24 | I5: 20 | K5: =IF(N(G5)>0,(N(H5)+N(I5)+N(J5))/G5,"") | L5: =IF(K5="","",IF(K5>=0.035,"Strong",IF(K5>=0.0256,"On par","Below"))) | M5: Reactions and comments as of 24 Mar 2026 (Gmail 'commented on your post'). Impressions not reported per post; its launch week had 794. Comment from John Froelich: 'very excited to have you on the team'.
A6: 2 | C6: =IF(B6="","",IF(MONTH(B6)<=3,"Q1",IF(MONTH(B6)<=6,"Q2",IF(MONTH(B6)<=9,"Q3","Q4")))) | K6: =IF(N(G6)>0,(N(H6)+N(I6)+N(J6))/G6,"") | L6: =IF(K6="","",IF(K6>=0.035,"Strong",IF(K6>=0.0256,"On par","Below")))
A7: 3 | C7: =IF(B7="","",IF(MONTH(B7)<=3,"Q1",IF(MONTH(B7)<=6,"Q2",IF(MONTH(B7)<=9,"Q3","Q4")))) | K7: =IF(N(G7)>0,(N(H7)+N(I7)+N(J7))/G7,"") | L7: =IF(K7="","",IF(K7>=0.035,"Strong",IF(K7>=0.0256,"On par","Below")))
A8: 4 | C8: =IF(B8="","",IF(MONTH(B8)<=3,"Q1",IF(MONTH(B8)<=6,"Q2",IF(MONTH(B8)<=9,"Q3","Q4")))) | K8: =IF(N(G8)>0,(N(H8)+N(I8)+N(J8))/G8,"") | L8: =IF(K8="","",IF(K8>=0.035,"Strong",IF(K8>=0.0256,"On par","Below")))
A9: 5 | C9: =IF(B9="","",IF(MONTH(B9)<=3,"Q1",IF(MONTH(B9)<=6,"Q2",IF(MONTH(B9)<=9,"Q3","Q4")))) | K9: =IF(N(G9)>0,(N(H9)+N(I9)+N(J9))/G9,"") | L9: =IF(K9="","",IF(K9>=0.035,"Strong",IF(K9>=0.0256,"On par","Below")))
A10: 6 | C10: =IF(B10="","",IF(MONTH(B10)<=3,"Q1",IF(MONTH(B10)<=6,"Q2",IF(MONTH(B10)<=9,"Q3","Q4")))) | K10: =IF(N(G10)>0,(N(H10)+N(I10)+N(J10))/G10,"") | L10: =IF(K10="","",IF(K10>=0.035,"Strong",IF(K10>=0.0256,"On par","Below")))
A11: 7 | C11: =IF(B11="","",IF(MONTH(B11)<=3,"Q1",IF(MONTH(B11)<=6,"Q2",IF(MONTH(B11)<=9,"Q3","Q4")))) | K11: =IF(N(G11)>0,(N(H11)+N(I11)+N(J11))/G11,"") | L11: =IF(K11="","",IF(K11>=0.035,"Strong",IF(K11>=0.0256,"On par","Below")))
A12: 8 | C12: =IF(B12="","",IF(MONTH(B12)<=3,"Q1",IF(MONTH(B12)<=6,"Q2",IF(MONTH(B12)<=9,"Q3","Q4")))) | K12: =IF(N(G12)>0,(N(H12)+N(I12)+N(J12))/G12,"") | L12: =IF(K12="","",IF(K12>=0.035,"Strong",IF(K12>=0.0256,"On par","Below")))
A13: 9 | C13: =IF(B13="","",IF(MONTH(B13)<=3,"Q1",IF(MONTH(B13)<=6,"Q2",IF(MONTH(B13)<=9,"Q3","Q4")))) | K13: =IF(N(G13)>0,(N(H13)+N(I13)+N(J13))/G13,"") | L13: =IF(K13="","",IF(K13>=0.035,"Strong",IF(K13>=0.0256,"On par","Below")))
A14: 10 | C14: =IF(B14="","",IF(MONTH(B14)<=3,"Q1",IF(MONTH(B14)<=6,"Q2",IF(MONTH(B14)<=9,"Q3","Q4")))) | K14: =IF(N(G14)>0,(N(H14)+N(I14)+N(J14))/G14,"") | L14: =IF(K14="","",IF(K14>=0.035,"Strong",IF(K14>=0.0256,"On par","Below")))
A15: 11 | C15: =IF(B15="","",IF(MONTH(B15)<=3,"Q1",IF(MONTH(B15)<=6,"Q2",IF(MONTH(B15)<=9,"Q3","Q4")))) | K15: =IF(N(G15)>0,(N(H15)+N(I15)+N(J15))/G15,"") | L15: =IF(K15="","",IF(K15>=0.035,"Strong",IF(K15>=0.0256,"On par","Below")))
A16: 12 | C16: =IF(B16="","",IF(MONTH(B16)<=3,"Q1",IF(MONTH(B16)<=6,"Q2",IF(MONTH(B16)<=9,"Q3","Q4")))) | K16: =IF(N(G16)>0,(N(H16)+N(I16)+N(J16))/G16,"") | L16: =IF(K16="","",IF(K16>=0.035,"Strong",IF(K16>=0.0256,"On par","Below")))
A17: 13 | C17: =IF(B17="","",IF(MONTH(B17)<=3,"Q1",IF(MONTH(B17)<=6,"Q2",IF(MONTH(B17)<=9,"Q3","Q4")))) | K17: =IF(N(G17)>0,(N(H17)+N(I17)+N(J17))/G17,"") | L17: =IF(K17="","",IF(K17>=0.035,"Strong",IF(K17>=0.0256,"On par","Below")))
... A40: 36 | C40: =IF(B40="","",IF(MONTH(B40)<=3,"Q1",IF(MONTH(B40)<=6,"Q2",IF(MONTH(B40)<=9,"Q3","Q4")))) | K40: =IF(N(G40)>0,(N(H40)+N(I40)+N(J40))/G40,"") | L40: =IF(K40="","",IF(K40>=0.035,"Strong",IF(K40>=0.0256,"On par","Below")))
A42: Rating rule: Strong = 3.5%+ engagement rate, On par = 2.56% to 3.5% (AuthoredUp median for small accounts), Below = under 2.56%. Engagement = reactions + comments + reposts.

Sheet Audience
A1: Audience: who saw your posts
A2: From the 'top viewers' panel in LinkedIn's weekly recap emails (weeks of 2 Mar, 23 Mar and 13 Apr). LinkedIn shows the top segment only, not percentages.
A4: Dimension | B4: Top segment | C4: Weeks it topped | D4: What it means for you | E4: Fit with Claude brand
A5: Industry | B5: IT Services and IT Consulting | C5: 3 of 3 | D5: Your reach sits with IT services peers, which is your past network. Good for credibility, weaker for buyers in sales ops and government. | E5: Partial
A6: Seniority | B6: Senior | C6: 3 of 3 | D6: Senior people already read you. Write for decision makers: outcomes, time saved, risk reduced. | E6: Strong
A7: Company size | B7: 501 to 1,000 employees | C7: 2 of 3 | D7: Mid-size firms are a good fit for Claude workflow consulting: big enough to have CRM mess, small enough to move fast. | E7: Strong
A8: Location | B8: Pune / Pimpri-Chinchwad Area | C8: 1 of 3 | D8: Your reach is local. Bramasol and most Claude buyers are US-based, so test posting in US morning hours too. | E8: Weak
A9: Missing | B9: Sales ops, RevOps, CRM admins, public sector | C9: 0 of 3 | D9: The people your brand is for did not show up in any recap. Topic-led content and commenting on their posts is how you reach them. | E9: Gap
A11: PROFILE SIGNALS FOUND
A12: Signal | B12: What we found | D12: Implication
A13: Headline (Apr to Jul) | B13: Sales Ops & Data Consultant | CRM Accuracy | Pipeline Visibility | Decision-Ready Data | D13: Clear sales ops positioning. No mention of Claude or AI, so the algorithm and visitors cannot link you to that topic.
A14: Display name history | B14: Shrikant Ahire > 'SK' > 'S. K.' > 'Shreekant Aahire' > 'Shrikant V Ahire' | D14: Five names in four months. This hurts name search, recognition and consistency. Pick one and keep it.
A15: Comments on others' posts | B15: At least 2 comments drew replies (25 Apr, 18 Jun) | D15: You comment occasionally. Research says daily comments are a top reach and lead source.

Sheet Diagnosis
A1: Diagnosis: what your Q1 and Q2 data says
A2: Ten findings from your own numbers, sorted by priority. Red = fix first. Amber = improve. Green = keep doing.
A4: # | B4: Rating | C4: Finding | D4: Evidence | E4: So what / fix | F4: Linked action
A5: 1 | B5: Red | C5: Posting volume was close to zero | D5: One original post identified in 26 weeks. No recap emails in Jan, Feb, May or most of June, which LinkedIn only sends when you have impressions. | E5: Volume is the biggest lever you have. Buffer found 2 to 5 posts a week adds about 1,182 impressions per post. Move to 3 posts a week. | F5: A1, A2
A6: 2 | B6: Red | C6: No Claude or AI content yet | D6: The only identified post was a job update. Headline mentions sales ops and data, not Claude. | E6: Your brand goal has no content behind it. Start a named weekly Claude series and update the headline. | F6: A3, A10
A7: 3 | B7: Red | C7: Reach collapsed after the one post | D7: Weekly impressions went 794, then 150, then 23, then about 3, then 73, then 22. | E7: Each post gets most of its reach in the first days. Without the next post, reach drops to almost nothing. Consistency matters more than any single hit. | F7: A1, A13
A8: 4 | B8: Red | C8: No analytics are being kept | D8: No LinkedIn export in Drive. Only 5 of 28 weeks have any numbers. | E8: You cannot improve what you cannot see. Export analytics on the first Monday of each month and log every post in Post Log. | F8: A16
A9: 5 | B9: Amber | C9: Name changed five times in four months | D9: Shrikant Ahire, SK, S. K., Shreekant Aahire, Shrikant V Ahire (security emails, Apr to Jun). | E9: Consistent naming helps search, recognition and the algorithm's topic matching. Choose one name and keep it. | F9: A10
A10: 6 | B10: Amber | C10: Audience is your old network, not your buyers | D10: Top viewers: IT Services, Senior, 501 to 1,000 staff, Pune. No sales ops, RevOps or public sector segments appear. | E10: Topic-led posts plus daily comments on sales ops and govtech leaders' posts will pull in the right audience. | F10: A8, A9
A11: 7 | B11: Amber | C11: Commenting is occasional | D11: Two comments on others' posts drew replies (25 Apr, 18 Jun). | E11: Comments of 15+ words carry 2 to 2.5x the weight of short ones. Do 5 thoughtful comments a day. | F11: A8
A12: 8 | B12: Green | C12: Your network rewards real news | D12: Job post week: 794 impressions, 23 reactions, 25 comments, 6.0% engagement. Benchmark median is 2.56%. | E12: People engage when you share something real. Use personal milestones and client results once a month. | F12: A14
A13: 9 | B13: Green | C13: Comments outnumber reactions | D13: 25 comments vs 23 reactions in the peak week; 20 comments on the job post. | E13: Comments are the signal LinkedIn values most. Ending posts with a specific question builds on this. | F13: A7
A14: 10 | B14: Green | C14: Senior, mid-size audience | D14: Senior seniority and 501 to 1,000 employee firms top the recaps. | E14: This is a good buyer profile for Claude workflow consulting. Write for decision makers. | F14: A3

Sheet Research Insights
A1: Research Insights: what the 2025 to 2026 data says
A2: 53 findings from named studies (van der Blom, AuthoredUp, Metricool, Socialinsider, Buffer, LinkedIn, Pangram Labs and others). Filter by Area or Confidence with the arrows in the header row.
A4: # | B4: Area | C4: Finding | D4: What it means for you | E4: Source | F4: Date | G4: Confidence | H4: Link
A5: 1 | B5: Algorithm | C5: Richard van der Blom's October 2025 Algorithm InSights report (about 1.8 million posts) found average reach fell about 47% between February and September 2025, with engagement down about 39% and follower growth down about 42%. | D5: Judge Q1/Q2 2026 results against a shrinking baseline, so flat impressions year on year may actually mean you outperformed the platform. | E5: Richard van der Blom, Algorithm InSights Report Oct 2025 (via Siecle Digital) | F5: 2025-10 | G5: High | H5: Open
A6: 2 | B6: Algorithm | C6: LinkedIn's research team published 360Brew, a 150-billion-parameter decoder-only model that handles ranking and recommendation across LinkedIn surfaces using natural-language descriptions of members and content. | D6: Profile text, headline and post wording are now read as language, so you should describe your niche (Claude for CRM, sales ops and public sector) in the same plain words every time. | E6: 360Brew paper, LinkedIn (arXiv 2501.16450) | F6: 2025-01 | G6: High | H6: Open
A7: 3 | B7: Algorithm | C7: In March 2026 LinkedIn announced an LLM-based retrieval and Generative Recommender ranking system that matches posts to viewers by topic embeddings and reads over 1,000 past interactions per member, increasing distribution beyond a creator's own network. | D7: Staying on two or three tightly related topics should help the system learn who your posts are for and show them to non-connections in sales ops and government tech. | E7: Search Engine Land coverage of LinkedIn Engineering announcement | F7: 2026-03 | G7: High | H7: Open
A8: 4 | B8: Algorithm | C8: LinkedIn engineering leadership (Tim Jurka) has said the feed is designed for relevance rather than virality, aiming to get the right knowledge to the right people rather than the largest audience. | D8: You should measure success by who engages (buyers, RevOps leaders, public sector managers) rather than raw impressions. | E8: Herdl summary of LinkedIn statements | F8: 2026-03 | G8: Medium | H8: Open
A9: 5 | B9: Algorithm | C9: Van der Blom's 2025 research reports that posts holding 61+ seconds of average dwell time reached about 15.6% engagement versus about 1.2% for posts skimmed in under 3 seconds. | D9: Write posts that reward reading to the end, such as step-by-step Claude workflows with a concrete result, rather than short opinion one-liners. | E9: Van der Blom 2025 data as reported by Contentin | F9: 2025-12 | G9: Medium | H9: Open
A10: 6 | B10: Algorithm | C10: Van der Blom's 2025 report is cited as finding that one save drives roughly 5 times the reach of a like and about 2 times that of a comment, and LinkedIn added saves and sends to post analytics in late 2025. | D10: Make reference-style content people want to keep (prompt templates, checklists, CRM audit steps) and track saves and sends as your main quality metric. | E10: Melanie Goodman summary of Van der Blom 2025; LinkedIn analytics update | F10: 2025-11 | G10: Medium | H10: Open
A11: 7 | B11: Algorithm | C11: Comments of 15 or more words are reported to carry roughly 2 to 2.5 times the weight of short comments, and generic comments like 'Great post' are treated as low value. | D11: End posts with a specific question that invites a real answer, and leave substantive comments yourself rather than short praise. | E11: Van der Blom 2025 as summarised by Contentin and Melanie Goodman | F11: 2025-11 | G11: Medium | H11: Open
A12: 8 | B12: Algorithm | C12: Practitioner summaries of van der Blom's work say about 70% of a post's reach is decided in the first 60 to 90 minutes and that author replies in the first 30 to 60 minutes lift comments and reach. | D12: Block 45 to 60 minutes after each post to reply to every comment with a full sentence. | E12: Contentin / Van der Blom summary; Melanie Goodman | F12: 2025-12 | G12: Medium | H12: Open
A13: 9 | B13: Algorithm | C13: A study of over 900,000 posts (Feb 2023 to Feb 2026) found posts with external links got 26.5% less reach on average, with the penalty growing from about 5% in 2023 to about 42% in 2025; LinkedIn officially says it does not penalise links by default. | D13: Keep YouTube and newsletter links out of the post body for reach-focused posts, and test link-in-comment versus no link for your own account. | E13: Ordinal link penalty study | F13: 2026-02 | G13: Medium | H13: Open
A14: 10 | B14: Algorithm | C14: Metricool's 2025 study of 577,000+ Company Page posts found link posts had 4.9% more impressions and 13.5% more interactions, which conflicts with personal-profile studies showing a link penalty. | D14: Treat the link penalty as likely for personal profiles but not absolute; run your own A/B test over a month before making a rule. | E14: Metricool 2025 LinkedIn Study (via Search Engine Journal) | F14: 2025-04 | G14: Medium | H14: Open
A15: 11 | B15: Algorithm | C15: Van der Blom reports that hashtags no longer give a reach boost, and LigoSocial's analysis of 134,522 posts from 1,499 profiles found hashtags neither hurt nor help much (1 to 2 hashtags about +3% within the same author). | D15: Use zero to three precise hashtags at most and spend the effort on the hook and topic clarity instead. | E15: LigoSocial hashtag research; Van der Blom | F15: 2026-09 | G15: Medium | H15: Open
A16: 12 | B16: Algorithm | C16: An analysis of 340 edited posts across 52 accounts found edits in the first 10 minutes had no measurable reach impact, major edits after 30 minutes cut impressions 30% to 50%, and adding or removing links after publishing cut final impressions by about 42%. | D16: Fix typos quickly but never add a link or rewrite a post after the first half hour. | E16: ConnectSafely edited-post analysis | F16: 2026-01 | G16: Low | H16: Open
... A57: 53 | B57: Monetisation | C57: A creator analysis on Substack reported getting 3 times more inbound leads from commenting than from posting. | D57: Treat strategic commenting on prospects' and partners' posts as a lead source, not just a reach tactic. | E57: Startup GTM Substack, Comment OS | F57: 2025-10 | G57: Low | H57: Open
A59: Confidence: High = official LinkedIn statement, peer-reviewed paper, or a study quoted consistently in several places. Medium = a named study reported second-hand. Low = a single vendor or anecdote. LinkedIn's own pages were blocked during research, so findings come from published summaries of each study.

Sheet Benchmarks
A1: Benchmarks: what good looks like
A2: Industry benchmarks from 2025 to 2026 studies. Column C holds the number used in formulas. Your figure sits in column E where we have one.
A4: Metric | B4: Tier / scope | C4: Value (numeric) | D4: Value as published | E4: You (Q1 + Q2) | F4: Source | G4: Link
A5: Median engagement rate per impression | B5: 0 to 1,000 followers | C5: 0.0256 | D5: 2.56% | E5: ='Weekly Data'!H33 | F5: AuthoredUp (372K posts, Sep 2025 to Feb 2026) | G5: Open
A6: Median engagement rate per impression | B6: 1,001 to 5,000 followers | C6: 0.0268 | D6: 2.68% | F6: AuthoredUp (372K posts, Sep 2025 to Feb 2026) | G6: Open
A7: Median engagement rate per impression | B7: 5,001 to 20,000 followers | C7: 0.0253 | D7: 2.53% | F7: AuthoredUp (372K posts, Sep 2025 to Feb 2026) | G7: Open
A8: Median impressions per post | B8: 0 to 1K followers | C8: 207 | D8: 207 | E8: =MEDIAN('Weekly Data'!$D$5:$D$32) | F8: MagicPost June 2026 (22,724 posts) | G8: Open
A9: Median impressions per post | B9: 1K to 5K followers | C9: 388 | D9: 388 | F9: MagicPost June 2026 (22,724 posts) | G9: Open
A10: Median impressions per post | B10: 5K to 10K followers | C10: 771 | D10: 771 | F10: MagicPost June 2026 (22,724 posts) | G10: Open
A11: Typical reach rate (impressions / followers) | B11: 0 to 1K followers | C11: 0.31 | D11: 31% | F11: The Shield Index Feb 2026 (50,000 posts) | G11: Open
A12: Typical reach rate (impressions / followers) | B12: 100K+ followers | C12: 0.06 | D12: 6% | F12: The Shield Index Feb 2026 (50,000 posts) | G12: Open
A13: Median engagement rate per follower | B13: 1K to 10K followers | C13: 0.0093 | D13: 0.93% (middle half 0.51% to 2.49%) | F13: Favikon (499 creators, Sep 2026) | G13: Open
A14: Median impressions per founder post / 90th percentile | B14: Founder personal profiles | C14: 502 | D14: 502 / 3,334 | E14: =MEDIAN('Weekly Data'!$D$5:$D$32) | F14: RevBoss (1,202 posts, Jan to Aug 2026) | G14: Open
A15: Average reach change Feb to Sep 2025 | B15: All profiles | C15: -0.47 | D15: -47% (engagement -39%, follower growth -42%) | F15: Van der Blom Algorithm InSights Oct 2025 | G15: Open
A16: Engagement rate: document/carousel | B16: Company Pages, 2026 | C16: 0.07 | D16: 7.0% | F16: Socialinsider 2026 | G16: Open
A17: Engagement rate: video | B17: Company Pages, 2026 | C17: 0.06 | D17: 6.0% | F17: Socialinsider 2026 | G17: Open
A18: Engagement rate: text only | B18: Company Pages, 2026 | C18: 0.045 | D18: 4.5% | F18: Socialinsider 2026 | G18: Open
A19: Engagement rate: external link posts | B19: Company Pages, 2026 | C19: 0.0325 | D19: 3.25% | F19: Socialinsider 2026 | G19: Open
A20: Reach change for posts with external links | B20: Personal and company, 2025 | C20: -0.42 | D20: -42% (vs -5% in 2023) | F20: Ordinal (900K+ posts) | G20: Open
A21: Extra impressions per post, 2 to 5 posts/week vs 1 | B21: All tiers | C21: 1182 | D21: +1,182 | F21: Buffer (2M+ posts, 94K accounts) | G21: Open
A22: YoY change in likes / comments / shares; overall engagement | B22: All accounts, 2026 | C22: 0.14 | D22: -13% / -17% / -10%; +14% | F22: Metricool 2026 (673,658 posts) | G22: Open
A23: Share of long posts (250+ words) fully AI-generated | B23: LinkedIn, Apr to Jun 2026 | C23: 0.41 | D23: 41% | F23: Pangram Labs (about 1M posts) | G23: Open
A24: Optimal post length (characters) | B24: Typical creators | D24: 800 to 1,100 top cluster; 1,301 to 2,500 +27% vs under 400 | F24: AuthoredUp | G24: Open
A26: Your follower count is not in any source we could reach, so compare against the 0 to 1K and 1K to 5K rows. Your 'You' figures are weekly totals, not per post, because LinkedIn's recap emails report by week.

Sheet Action Plan
A1: Action Plan: next 90 days (5 Oct to 31 Dec 2026)
A2: 18 actions in priority order. P1 = do this week. P2 = start this month. P3 = by December. Update the Status column as you go.
A4: ID | B4: Priority | C4: Area | D4: Action | E4: How to do it | F4: Target / metric | G4: Deadline | H4: Status | I4: Evidence (see Research Insights)
A5: A1 | B5: P1 | C5: Consistency | D5: Post 3 times a week, every week | E5: Tue, Wed, Thu. Batch-write on Sunday using the Content Calendar tab. Never skip two days in a row. | F5: 36 posts by 31 Dec | G5: 46307 | H5: Not started | I5: Buffer: 2 to 5 posts a week adds about 1,182 impressions per post
A6: A2 | B6: P1 | C6: Consistency | D6: Protect 60 minutes after each post | E6: Block the hour in your calendar. Reply to every comment with a full sentence. | F6: 100% of comments replied to within 1 hour | G6: 46307 | H6: Not started | I6: About 70% of reach is decided in the first 60 to 90 minutes
A7: A3 | B7: P1 | C7: Positioning | D7: Launch a named weekly series: 'Claude for Sales Ops' | E7: Every Tuesday: one real workflow (CRM clean-up, pipeline report, call notes to CRM). Show the before, the prompt, and the after with numbers. | F7: 13 episodes; at least 3 above 388 impressions | G7: 46308 | H7: Not started | I7: Brand24: best Claude content is builds and workflow wins; LLM ranking rewards a consistent topic
A8: A4 | B8: P1 | C8: Format | D8: Make carousels your main teaching format | E8: 8 slides: hook, problem, 5 steps, result. One template in Canva. Turn each YouTube video into one carousel. | F8: 1 carousel a week; engagement rate above 3.5% | G8: 46308 | H8: Not started | I8: Socialinsider: carousels 7.0% vs text 4.5%; Metricool: carousels top reach
A9: A5 | B9: P1 | C9: Writing | D9: Write in your own voice, not AI voice | E9: Use Claude to draft and research, then rewrite. Run every post through your humanize-post skill. Add one personal detail per post. | F9: 0 posts that read as AI-written | G9: 46307 | H9: Not started | I9: Pangram: 41% of long posts are AI-written; Originality: AI posts get 45% less engagement
A10: A6 | B10: P1 | C10: Writing | D10: First line under 60 characters with a specific result | E10: Example: 'Claude cleaned 4,000 CRM records in 20 minutes.' Lead with the number. | F10: Every post | G10: 46307 | H10: Not started | I10: AuthoredUp: hooks under 60 characters predict conversations
A11: A7 | B11: P1 | C11: Engagement | D11: End every post with one specific question | E11: Ask something only a practitioner can answer, for example 'Which CRM field causes your team the most rework?' | F11: Average 5+ comments per post | G11: 46307 | H11: Not started | I11: Comments of 15+ words weigh 2 to 2.5x more
A12: A8 | B12: P1 | C12: Engagement | D12: Comment daily on 5 posts by your target audience | E12: 15 to 20 minutes a day. Sales ops, RevOps, CRM and govtech leaders. 15+ words, add a fact or an example. No AI comment tools. | F12: 25 quality comments a week | G12: 46307 | H12: Not started | I12: LinkedIn: weekly commenting can triple profile views; automated comments are now hidden
A13: A9 | B13: P2 | C13: Audience | D13: Build a list of 50 target accounts to follow and engage | E13: 30 sales ops / RevOps leaders, 10 govtech leaders, 10 Claude and AI creators. Ring the bell on 20 of them. | F13: List built; profile views from target industries rising | G13: 46314 | H13: Not started | I13: B2B Institute: 95% of buyers are out of market; stay visible
A14: A10 | B14: P1 | C14: Profile | D14: Fix name and headline | E14: Name: 'Shrikant Ahire' and keep it. Headline idea: 'Sales Ops and CRM Consultant | Practical Claude workflows for sales and public sector teams'. | F14: Done; no further name changes | G14: 46305 | H14: Not started | I14: LLM ranking reads profile text; consistency aids search
A15: A11 | B15: P2 | C15: Profile | D15: Update Featured, banner and custom button | E15: Featured: best carousel, your YouTube channel, newsletter. Banner states the offer. Custom button to YouTube or booking link. | F15: Profile views per week up 50% | G15: 46314 | H15: Not started | I15: LinkedIn Creator tools; photo profiles get 21x more views
A16: A12 | B16: P2 | C16: Format | D16: Post one 30 to 90 second Claude demo video a week | E16: Screen recording with captions, cut from your YouTube videos. Native upload, vertical. | F16: 1 video a week; track views and watch time | G16: 46321 | H16: Not started | I16: LinkedIn video viewing up 36%; van der Blom: video held up best
... A22: A18 | B22: P3 | C22: Pipeline | D22: Turn engagement into conversations | E22: When someone engages twice, send a short personal note with a relevant resource. No pitch. | F22: 10 conversations; 2 discovery calls | G22: 46387 | H22: Not started | I22: Edelman-LinkedIn: 9 in 10 buyers more receptive to consistent publishers
A24: Progress | C24: =COUNTIF(H5:H22,"Done")&" of "&ROWS(H5:H22)&" actions done" | D24: =COUNTIF(H5:H22,"Done")/ROWS(H5:H22)

Sheet Content Calendar
A1: Content Calendar: 13 weeks, 3 posts a week (Oct to Dec 2026)
A2: Tuesday = 'Claude for Sales Ops' carousel. Wednesday = sales ops, CRM or public sector insight (text + image). Thursday = rotating: short video, personal story, poll or client result. Hooks are starting points; rewrite in your voice.
A4: Week | B4: Date | C4: Day | D4: Format | E4: Pillar | F4: Topic | G4: Hook idea (under 60 characters) | H4: Done?
A5: 1 | B5: 46301 | C5: Tue | D5: Carousel | E5: Claude how-to | F5: Clean duplicate CRM contacts with Claude | G5: Claude found 312 duplicate contacts in 4 minutes.
A6: 1 | B6: 46302 | C6: Wed | D6: Text + image | E6: Sales ops / CRM insight | F6: Why pipeline reports lie: the 3 fields reps skip | G6: Your pipeline report is wrong in 3 places.
A7: 1 | B7: 46303 | C7: Thu | D7: Personal | E7: Personal milestone | F7: 7 months at Bramasol: what changed in how I work with AI | G7: Seven months in. Here is what Claude changed.
A8: 2 | B8: 46308 | C8: Tue | D8: Carousel | E8: Claude how-to | F8: Turn messy call notes into clean CRM updates | G8: Call notes to CRM in 90 seconds.
A9: 2 | B9: 46309 | C9: Wed | D9: Text + image | E9: Public sector | F9: What government platforms get wrong about data entry | G9: Government forms create bad data by design.
A10: 2 | B10: 46310 | C10: Thu | D10: Poll | E10: Opinion | F10: Which Claude workflow should I build next? | G10: Pick the next Claude workflow I build.
A11: 3 | B11: 46315 | C11: Tue | D11: Carousel | E11: Claude how-to | F11: Weekly pipeline summary for your VP, with Claude | G11: My VP's Monday report now takes 6 minutes.
A12: 3 | B12: 46316 | C12: Wed | D12: Text + image | E12: Sales ops / CRM insight | F12: The real cost of a dirty CRM (with numbers) | G12: Bad CRM data cost one team 11 hours a week.
A13: 3 | B13: 46317 | C13: Thu | D13: Video | E13: Claude how-to | F13: 60-second demo: Claude reads a CRM export | G13: Watch Claude audit a CRM export live.
A14: 4 | B14: 46322 | C14: Tue | D14: Carousel | E14: Claude how-to | F14: Poll result: build the workflow your audience chose | G14: You voted. I built it.
A15: 4 | B15: 46323 | C15: Wed | D15: Text + image | E15: Client story | F15: Before and after: one client's lead routing | G15: Lead routing went from 2 days to 2 hours.
A16: 4 | B16: 46324 | C16: Thu | D16: Personal | E16: Personal milestone | F16: What psychology taught me about sales data | G16: Psychology explains why reps skip CRM fields.
... A43: 13 | B43: 46387 | C43: Thu | D43: Poll | E43: Opinion | F43: What should the 2027 series cover? | G43: Choose next year's Claude series topic.
A45: Posted so far | D45: =COUNTIF(H5:H43,"Yes")&" of "&ROWS(H5:H43)

Sheet Tracker
A1: Tracker: weekly scorecard vs targets (Oct to Dec 2026)
A2: Every Monday, fill the yellow cells from LinkedIn Analytics (last 7 days). Cells turn green when you hit the target in row 5 and red when you miss it.
A4: Week start | B4: Posts | C4: Impressions | D4: Reactions | E4: Comments | F4: Saves + sends | G4: Comments given | H4: New followers | I4: Profile views | J4: Eng. rate | K4: Impr. per post
A5: TARGET | B5: 3 | C5: 1200 | E5: 15 | G5: 25 | H5: 10 | I5: 30 | J5: 0.035 | K5: 400
A6: 46300 | J6: =IF(N(C6)>0,(N(D6)+N(E6))/C6,"") | K6: =IF(N(B6)>0,C6/B6,"")
A7: 46307 | J7: =IF(N(C7)>0,(N(D7)+N(E7))/C7,"") | K7: =IF(N(B7)>0,C7/B7,"")
A8: 46314 | J8: =IF(N(C8)>0,(N(D8)+N(E8))/C8,"") | K8: =IF(N(B8)>0,C8/B8,"")
A9: 46321 | J9: =IF(N(C9)>0,(N(D9)+N(E9))/C9,"") | K9: =IF(N(B9)>0,C9/B9,"")
A10: 46328 | J10: =IF(N(C10)>0,(N(D10)+N(E10))/C10,"") | K10: =IF(N(B10)>0,C10/B10,"")
A11: 46335 | J11: =IF(N(C11)>0,(N(D11)+N(E11))/C11,"") | K11: =IF(N(B11)>0,C11/B11,"")
A12: 46342 | J12: =IF(N(C12)>0,(N(D12)+N(E12))/C12,"") | K12: =IF(N(B12)>0,C12/B12,"")
A13: 46349 | J13: =IF(N(C13)>0,(N(D13)+N(E13))/C13,"") | K13: =IF(N(B13)>0,C13/B13,"")
A14: 46356 | J14: =IF(N(C14)>0,(N(D14)+N(E14))/C14,"") | K14: =IF(N(B14)>0,C14/B14,"")
A15: 46363 | J15: =IF(N(C15)>0,(N(D15)+N(E15))/C15,"") | K15: =IF(N(B15)>0,C15/B15,"")
A16: 46370 | J16: =IF(N(C16)>0,(N(D16)+N(E16))/C16,"") | K16: =IF(N(B16)>0,C16/B16,"")
A17: 46377 | J17: =IF(N(C17)>0,(N(D17)+N(E17))/C17,"") | K17: =IF(N(B17)>0,C17/B17,"")
A18: 46384 | J18: =IF(N(C18)>0,(N(D18)+N(E18))/C18,"") | K18: =IF(N(B18)>0,C18/B18,"")
A19: Q4 total | B19: =SUM(B6:B18) | C19: =SUM(C6:C18) | D19: =SUM(D6:D18) | E19: =SUM(E6:E18) | F19: =SUM(F6:F18) | G19: =SUM(G6:G18) | H19: =SUM(H6:H18) | I19: =SUM(I6:I18) | J19: =IF(N(C19)>0,(D19+E19)/C19,"") | K19: =IF(N(B19)>0,C19/B19,"")
A20: vs Q1 + Q2 recorded | B20: =B19-COUNTA('Post Log'!$B$5:$B$40) | C20: =C19-SUM('Weekly Data'!$D$5:$D$32) | D20: =D19-SUM('Weekly Data'!$E$5:$E$32) | E20: =E19-SUM('Weekly Data'!$F$5:$F$32)
A22: Where to find each number: LinkedIn > Me > Posts & Activity > Analytics. Impressions, Reactions, Comments, Saves and Sends are on the Content tab; New followers on the Followers tab; Profile views on 'Profile viewers'. 'Comments given' is your own count of comments on others' posts.

Sheet Sources & Gaps
A1: Sources & Gaps: where every number came from
A2: Gathered by two research agents on 4 Oct 2026. Agent 1 searched your Gmail, Google Drive and the public web for your data. Agent 2 researched LinkedIn algorithm, benchmark and AI content studies.
A4: Source checked | B4: What it gave us | C4: Useful?
A5: Google Drive search (title contains LinkedIn/Content_/AggregateAnalytics/analytics; fullText Impressions/Engagements; owned xlsx/csv/Sheets) | B5: No LinkedIn analytics exports. Only unrelated files (a shared 'Linkedin Lead Gen.json' n8n workflow, course PDFs, other people's guides). User owns no spreadsheets/CSVs in Drive. | C5: No
A6: Gmail from:linkedin.com after:2026/01/01 before:2026/07/20 (also in:anywhere) | B6: 29 threads total, all opened or triaged. 5 weekly creator analytics recaps (weeks of 03/02, 03/23, 03/30, 04/13, 06/29) with impressions/comments/reactions read from HTML body; 2 'commented on your post' notifications with running reaction/comment totals for one post; 3 'replied to your comment' notifications (your comments on others' posts); rest are security, job alerts, newsletters, network digests, Premium/survey promos. No Jan or Feb content/analytics emails at all. | C6: Yes
A7: Gmail keyword search (linkedin + impressions/profile views/viewed your profile/search appearances/followers/your post), 2025-12-25 to 2026-07-20 | B7: Nothing beyond the same weekly recaps and comment notifications; no profile-view, search-appearance or follower-milestone emails exist in the mailbox for the window. | C7: No
A8: WebSearch: "Shrikant Ahire" LinkedIn 2026; "shrikant-ahire87" OR "Shrikant Ahire" Bramasol; site:linkedin.com/posts shrikant-ahire87 | B8: No publicly indexed posts or profile for this person; results were other people named Shrikant/Ahire. | C8: No
A9: WebFetch linkedin.com/in/shrikant-ahire87/recent-activity | B9: Blocked by egress proxy (EGRESS_BLOCKED), as expected. | C9: No
A11: DATA GAPS AND HOW TO CLOSE THEM
A12: No LinkedIn analytics export (Content_/AggregateAnalytics xlsx) exists in Google Drive; exact monthly impressions, members reached, engagements and followers are unavailable. Export from LinkedIn > Analytics > Content/Followers (Past 365 days) would fill this.
A13: No follower counts (total or new) in any source.
A14: No profile-view or search-appearance numbers in any source (no 'who viewed your profile' or search-appearance emails received).
A15: No weekly recaps for weeks 03/09-03/22, 04/06-04/12, 04/20-06/28; LinkedIn only emails recaps intermittently, so monthly totals cannot be summed.
A16: Impressions for the Bramasol post itself are not stated (only weekly totals); reposts unknown.
A17: Whether any other posts were published in Q1/Q2 cannot be confirmed; LinkedIn notifications only surfaced the one post.
A18: linkedin.com is blocked by the proxy and no posts are publicly indexed by search engines, so post content, format and visible counts could not be verified on the web.
A20: HOW TO EXPORT YOUR LINKEDIN DATA (5 minutes)
A21: 1. On desktop, go to Me > Posts & Activity > Analytics (or linkedin.com/analytics/creator/content).
A22: 2. Content tab: set the range to 1 Jan to 30 Jun 2026 (or Past 365 days) and click Export. The file has daily impressions and engagements, top posts and demographics.
A23: 3. Followers tab: export the same range for daily new followers and total followers.
... A25: 5. Or save the files to Google Drive with 'LinkedIn' in the name and ask Claude to fill the workbook for you.
